eventbus/__init__.py
eventbus/client.py
eventbus/handlers.py
eventbus/registry.py
eventbus/routes.py
eventbus/worker.py
eventbus_sdk-1.0.13.dist-info/METADATA
eventbus_sdk-1.0.13.dist-info/WHEEL
eventbus_sdk-1.0.13.dist-info/top_level.txt
eventbus_sdk-1.0.13.dist-info/RECORD
